LICENSE.rst
MANIFEST.in
README.rst
setup.py
aesfield/__init__.py
aesfield/default.py
aesfield/field.py
aesfield/models.py
aesfield/sample.key
aesfield/tests.py
aesfield/management/__init__.py
aesfield/management/commands/__init__.py
aesfield/management/commands/generate_aes_keys.py
django_mysql_aesfield.egg-info/PKG-INFO
django_mysql_aesfield.egg-info/SOURCES.txt
django_mysql_aesfield.egg-info/dependency_links.txt
django_mysql_aesfield.egg-info/not-zip-safe
django_mysql_aesfield.egg-info/top_level.txt