Metadata-Version: 1.0
Name: django-mysql-aesfield
Version: 0.2.1
Summary: Django Model Field that supports AES encryption in MySQL
Home-page: https://github.com/andymckay/django-mysql-aesfield
Author: Andy McKay
Author-email: andym@mozilla.com
License: BSD
Platform: UNKNOWN
Classifier: Intended Audience :: Developers
Classifier: Natural Language :: English
Classifier: Operating System :: OS Independent
Classifier: Framework :: Django
